git_autograder/__init__.py
git_autograder/branch.py
git_autograder/commit.py
git_autograder/encoder.py
git_autograder/exception.py
git_autograder/exercise.py
git_autograder/exercise_config.py
git_autograder/output.py
git_autograder/py.typed
git_autograder/reflog_entry.py
git_autograder/remote.py
git_autograder/status.py
git_autograder/version.py
git_autograder/answers/__init__.py
git_autograder/answers/answers.py
git_autograder/answers/answers_parser.py
git_autograder/answers/answers_record.py
git_autograder/answers/rules/__init__.py
git_autograder/answers/rules/answer_rule.py
git_autograder/answers/rules/contains_list_rule.py
git_autograder/answers/rules/contains_value_rule.py
git_autograder/answers/rules/has_exact_list_rule.py
git_autograder/answers/rules/has_exact_value_rule.py
git_autograder/answers/rules/not_empty_rule.py
git_autograder/diff/__init__.py
git_autograder/diff/diff.py
git_autograder/diff/diff_helper.py
git_autograder/helpers/__init__.py
git_autograder/helpers/branch_helper.py
git_autograder/helpers/commit_helper.py
git_autograder/helpers/file_helper.py
git_autograder/helpers/remote_helper.py
git_autograder/repo/__init__.py
git_autograder/repo/null_repo.py
git_autograder/repo/repo.py
git_autograder/repo/repo_base.py
git_autograder-6.6.0.dist-info/METADATA
git_autograder-6.6.0.dist-info/WHEEL
git_autograder-6.6.0.dist-info/licenses/LICENSE
git_autograder-6.6.0.dist-info/RECORD
