Metadata-Version: 2.4
Name: git-autograder
Version: 6.6.0
Summary: Library for autograding Git repositories
Project-URL: Homepage, https://github.com/git-mastery/git-autograder.git
Project-URL: Repository, https://github.com/git-mastery/git-autograder.git
Project-URL: Issues, https://github.com/git-mastery/git-autograder/issues
Author-email: "Jiahao, Woo" <woojiahao1234@gmail.com>
License: MIT License
License-File: LICENSE
Classifier: Development Status :: 4 - Beta
Classifier: Intended Audience :: Developers
Classifier: Programming Language :: Python :: 3.13
Classifier: Topic :: Software Development
Requires-Python: >=3.13
Requires-Dist: difflib-parser
Requires-Dist: gitpython
Requires-Dist: pytz
Requires-Dist: repo-smith
Requires-Dist: types-pytz
